jupyterhub_simplespawner-0.1.dist-info/DESCRIPTION.rst
jupyterhub_simplespawner-0.1.dist-info/METADATA
jupyterhub_simplespawner-0.1.dist-info/RECORD
jupyterhub_simplespawner-0.1.dist-info/WHEEL
jupyterhub_simplespawner-0.1.dist-info/metadata.json
jupyterhub_simplespawner-0.1.dist-info/top_level.txt
simplespawner/__init__.py
simplespawner/simplespawner.py
