Metadata-Version: 2.0
Name: jupyterhub-simplespawner
Version: 0.1
Summary: Simple Local Process spawner for JupyterHub
Home-page: https://github.com/yuvipanda/jupyterhub-simplespawner
Author: Yuvi Panda
Author-email: yuvipanda@riseup.net
License: 3 Clause BSD
Platform: UNKNOWN
